srinadhch07/BAv2.py
srinadhch07/__init__.py
srinadhch07/hello.py
srinadhch07-0.26.dist-info/LICENSE
srinadhch07-0.26.dist-info/METADATA
srinadhch07-0.26.dist-info/WHEEL
srinadhch07-0.26.dist-info/top_level.txt
srinadhch07-0.26.dist-info/RECORD
