Metadata-Version: 2.1
Name: srinadhch07
Version: 0.26
Summary: BAv2
Home-page: https://github.com/Srinadhch07/BAv2.git
Author: srinadhch07
Author-email: <srinadhc07@gmail.com>
License: MIT
Keywords: python,video,stream,video stream,camera stream,sockets
Classifier: Development Status :: 1 - Planning
Classifier: Intended Audience :: Developers
Classifier: Programming Language :: Python :: 3
Classifier: Operating System :: Unix
Classifier: Operating System :: MacOS :: MacOS X
Classifier: Operating System :: Microsoft :: Windows
Classifier: Intended Audience :: Developers
Classifier: Topic :: Software Development :: Build Tools
Classifier: License :: OSI Approved :: MIT License
Classifier: Programming Language :: Python :: 3.8
Classifier: Programming Language :: Python :: 3.9
Classifier: Programming Language :: Python :: 3.10
License-File: LICENSE
Requires-Dist: Pillow ~=9.3.0
Requires-Dist: pyautogui ~=0.9.53
Requires-Dist: requests ~=2.28.1
Requires-Dist: wikipedia ~=1.4.0
Requires-Dist: paperclip ~=2.6.1
Requires-Dist: flask ~=2.2.2
Requires-Dist: setuptools ~=62.1.0
Requires-Dist: pyperclip ~=1.8.2
Requires-Dist: keyboard ~=0.13.5
